pySimulator/MIMO_2x3.cpython-313-x86_64-linux-gnu.so
pySimulator/QtGUI.cpython-313-x86_64-linux-gnu.so
pySimulator/SISO.cpython-313-x86_64-linux-gnu.so
pySimulator/SISO_DVPrd.cpython-313-x86_64-linux-gnu.so
pySimulator/SISO_LPV.cpython-313-x86_64-linux-gnu.so
pySimulator/SISO_int.cpython-313-x86_64-linux-gnu.so
pySimulator/__init__.py
pySimulator/shellmodel.cpython-313-x86_64-linux-gnu.so
pySimulator/uawidget_pyidh.cpython-313-x86_64-linux-gnu.so
pySimulator/uaworker_pyidh.cpython-313-x86_64-linux-gnu.so
pySimulator/pics/pet.ico
pySimulator/pics/pet.svg
taiji_pysimulator-2.2.0.dist-info/METADATA
taiji_pysimulator-2.2.0.dist-info/WHEEL
taiji_pysimulator-2.2.0.dist-info/top_level.txt
taiji_pysimulator-2.2.0.dist-info/RECORD
