Metadata-Version: 2.4
Name: taiji-pysimulator
Version: 2.2.0
Summary: pySimulator GUI tools
Author-email: Kangkang Zhang <kkzhang3@hotmail.com>
Requires-Python: >=3.12
Requires-Dist: PyQt5>=5.15
Requires-Dist: pyyaml
Requires-Dist: tsdbpy
Requires-Dist: tjdcs
Requires-Dist: OPCGatePy
Requires-Dist: pyidh
Requires-Dist: psycopg-binary
Provides-Extra: dev
Requires-Dist: pytest; extra == "dev"
